chdir/__init__.py
chdir-1.0.0.dist-info/LICENSE
chdir-1.0.0.dist-info/METADATA
chdir-1.0.0.dist-info/WHEEL
chdir-1.0.0.dist-info/top_level.txt
chdir-1.0.0.dist-info/RECORD
