Metadata-Version: 2.1
Name: chdir
Version: 1.0.0
Summary: Tiny library for setting the working directory to the location of a Python script.
Home-page: https://github.com/CabbageDevelopment/chdir
Author: Sam McCormack
Author-email: cabbagedevelopment@gmail.com
License: UNKNOWN
Project-URL: Source, https://github.com/CabbageDevelopment/chdir
Platform: UNKNOWN
Classifier: Intended Audience :: Developers
Classifier: License :: OSI Approved :: MIT License
Classifier: Programming Language :: Python :: 3.6
Classifier: Programming Language :: Python :: 3.7
Classifier: Programming Language :: Python :: 3.8
Requires-Python: ~=3.6
